git_lfs_http_mirror.py
git_lfs_http_mirror-0.0.7.dist-info/METADATA
git_lfs_http_mirror-0.0.7.dist-info/WHEEL
git_lfs_http_mirror-0.0.7.dist-info/licenses/LICENSE
git_lfs_http_mirror-0.0.7.dist-info/RECORD
