Metadata-Version: 2.1
Name: git-lfs-http-mirror
Version: 0.0.7
Summary: Simple Python server to serve a read only HTTP mirror of git repositories that use Large File Storage (LFS)
Project-URL: Homepage, https://github.com/uktrade/git-lfs-http-mirror
Author-email: Department for International Trade <sre@digital.trade.gov.uk>
License-File: LICENSE
Classifier: License :: OSI Approved :: MIT License
Classifier: Programming Language :: Python :: 3
Classifier: Topic :: Software Development :: Version Control :: Git
Requires-Python: >=3.7.4
Requires-Dist: click>=8.0.1
Requires-Dist: httpx>=0.23.1
Requires-Dist: hypercorn>=0.14.3
Requires-Dist: quart>=0.19.4
